resaid/__init__.py
resaid/database.py
resaid/dca.py
resaid/econ.py
resaid-0.2.9.dist-info/licenses/LICENSE
resaid-0.2.9.dist-info/METADATA
resaid-0.2.9.dist-info/WHEEL
resaid-0.2.9.dist-info/top_level.txt
resaid-0.2.9.dist-info/RECORD
