Metadata-Version: 2.4
Name: resaid
Version: 0.2.9
Summary: Comprehensive reservoir engineering tools for decline curve analysis and production forecasting
Home-page: https://github.com/gregeasley/resaid
Author: Greg Easley
Author-email: greg@easley.dev
License: MIT
Project-URL: Bug Tracker, https://github.com/gregeasley/resaid/issues
Keywords: reservoir engineering,decline curve analysis,production forecasting,oil and gas,DCA,arps
Classifier: Development Status :: 4 - Beta
Classifier: Intended Audience :: Science/Research
Classifier: Topic :: Scientific/Engineering
Classifier: Programming Language :: Python :: 3
Classifier: Programming Language :: Python :: 3.8
Classifier: Programming Language :: Python :: 3.9
Classifier: Programming Language :: Python :: 3.10
Classifier: Programming Language :: Python :: 3.11
Classifier: License :: OSI Approved :: MIT License
Classifier: Operating System :: OS Independent
Requires-Python: >=3.8
License-File: LICENSE
Requires-Dist: numpy>=1.22
Requires-Dist: pandas>=1.5.3
Requires-Dist: scipy>=1.0.0
Requires-Dist: statsmodels>=0.13.5
Requires-Dist: python-dateutil>=2.8.0
Requires-Dist: tqdm>=4.65.0
Requires-Dist: pyodbc>=4.0.0
Requires-Dist: jpype1>=1.0.0
Requires-Dist: pytopspeed-modernized>=1.1.0
Dynamic: author
Dynamic: author-email
Dynamic: classifier
Dynamic: description
Dynamic: description-content-type
Dynamic: home-page
Dynamic: keywords
Dynamic: license
Dynamic: license-file
Dynamic: project-url
Dynamic: requires-dist
Dynamic: requires-python
Dynamic: summary
